Workbook
Name ACCOUNTS: #REF!
Name NAVISION: #REF!
Name REFS: #REF!

Sheet CC
A1: Date | B1: Description | C1: Amount | D1: Extended Details | E1: Appears On Your Statement As | F1: Address | G1: City/State | H1: Zip Code | I1: Country | J1: Reference | K1: Category | L1: CC Name | M1: G/L Account No
A2: 45668 | B2: ONLINE PAYMENT - THANK YOU | C2: -12021.51 | D2: ONLINE PAYMENT - THANK YOU | E2: ONLINE PAYMENT - THANK YOU | J2: '320250110186972138' | L2: DELTARESERVE | M2: =VLOOKUP(SUBSTITUTE(J2,"'",""),Sheet1!L:M,2,FALSE) -> #N/A
A3: 45668 | B3: ADOBE SYSTEMS Adobe SAN JOSE CA | C3: 21.64 | D3: 567960456 www.adobe.com ADOBE SYSTEMS Adobe Systems SAN JOSE CA Description : 0 Price : 0.1999 www.adobe.com | E3: ADOBE SYSTEMS Adobe SAN JOSE CA | F3: 801 N 34TH ST | G3: SEATTLE WA | H3: 98103 | I3: UNITED STATES | J3: '320250120216930217' | K3: Merchandise & Supplies-Mail Order | L3: AMEXPLATINUM | M3: =VLOOKUP(SUBSTITUTE(J3,"'",""),Sheet1!L:M,2,FALSE) -> 64100
A4: 45668 | B4: GOOGLE *ISHARINGSOFT G.CO/HELPPAY# CA | C4: 16.04 | D4: A0YWKMVS DIGITAL GOODS: APPS GOOGLE *ISHARINGSOFT G.CO/HELPPAY# CA DIGITAL GOODS: APPS | E4: GOOGLE *ISHARINGSOFT G.CO/HELPPAY# CA | F4: 1600 AMPHITHEATRE PKWY | G4: MOUNTAIN VIEW CA | H4: 94043-1351 | I4: UNITED STATES | J4: 320250120218752716' | K4: Business Services-Internet Services | L4: DELTARESERVE | M4: =VLOOKUP(SUBSTITUTE(J4,"'",""),Sheet1!L:M,2,FALSE) -> 64100
A5: 45669 | B5: UBER | C5: 28.32 | D5: FG9QDJ8X LM5CYPCR 10013 Uber Trip help.uber.com CA LM5CYPCR 10013 | E5: Uber Trip help.uber.com CA | F5: 1455 MARKET ST 4TH FLOOR | G5: SAN FRANCISCO CA | H5: 94103 | I5: UNITED STATES | J5: '320250120213109403' | K5: Transportation-Taxis & Coach | L5: DELTARESERVE | M5: =VLOOKUP(SUBSTITUTE(J5,"'",""),Sheet1!L:M,2,FALSE) -> 61130
A6: 45669 | B6: FACEBK *META VERIFIEFB.ME/CC CA | C6: 11.99 | D6: 92545376346 DGTL CONTENT FACEBK *META VERIFIED FB.ME/CC CA DGTL CONTENT | E6: FACEBK *META VERIFIEFB.ME/CC CA | F6: 1 HACKER WAY | G6: MENLO PARK CA | H6: 94025 | I6: UNITED STATES | J6: '320250120231674656' | K6: Business Services-Office Supplies | L6: AMEXPLATINUM | M6: =VLOOKUP(SUBSTITUTE(J6,"'",""),Sheet1!L:M,2,FALSE) -> 54820
A7: 45669 | B7: WEGMANS ASTOR PLACE NEW YORK NY | C7: 63.09 | D7: W15608601385854293656 WEGMANS ASTOR PLACE 156 000000156 NEW YORK NY 5854293656 | E7: WEGMANS ASTOR PLACE NEW YORK NY | F7: 770 BROADWAY | G7: NEW YORK NY | H7: 10003 | I7: UNITED STATES | J7: '320250130246487755' | K7: Merchandise & Supplies-Groceries | L7: AMEXPLATINUM | M7: =VLOOKUP(SUBSTITUTE(J7,"'",""),Sheet1!L:M,2,FALSE) -> 54820
A8: 45670 | B8: ONLINE PAYMENT - THANK YOU | C8: -3000 | D8: ONLINE PAYMENT - THANK YOU | E8: ONLINE PAYMENT - THANK YOU | J8: '320250130233557937' | L8: AMEXPLATINUM | M8: =VLOOKUP(SUBSTITUTE(J8,"'",""),Sheet1!L:M,2,FALSE) -> #N/A
A9: 45670 | B9: LINKEDIN SN P3704854MOUNTAIN VIEW | C9: 40.58 | D9: P370485424 SUBSCRIPTIONS LINKEDIN SN P370485424 MOUNTAIN VIEW SUBSCRIPTIONS | E9: LINKEDIN SN P3704854MOUNTAIN VIEW | F9: 2029 STIERLIN CT STE 200 | G9: MOUNTAIN VIEW CA | H9: 94043-4655 | I9: UNITED STATES | J9: '320250130237878130' | K9: Merchandise & Supplies-Internet Purchase | L9: AMEXPLATINUM | M9: =VLOOKUP(SUBSTITUTE(J9,"'",""),Sheet1!L:M,2,FALSE) -> 61100
A10: 45671 | B10: IN *HEIDI KLING, PHDNEW YORK NY | C10: 300 | D10: 014IAAGAST48289 100033 IN *HEIDI KLING, PHD NEW YORK NY 8289 100033 | E10: IN *HEIDI KLING, PHDNEW YORK NY | F10: 18 EAST 16TH ST RM 503 | G10: NEW YORK NY | H10: 10003-3111 | I10: UNITED STATES | J10: '320250140261104869' | K10: Business Services-Health Care Services | L10: AMEXPLATINUM | M10: =VLOOKUP(SUBSTITUTE(J10,"'",""),Sheet1!L:M,2,FALSE) -> 54820
A11: 45671 | B11: PATREON* MEMBERSHIP SAN FRANCISCO CA | C11: 20.18 | D11: I2DMCP00098 SUPPORT@PATREON.COM PATREON* MEMBERSHIP 523885 SAN FRANCISCO CA SUPPORT@PATREON.COM | E11: PATREON* MEMBERSHIP SAN FRANCISCO CA | F11: 600 TOWNSEND 5TH FLOOR | G11: SAN FRANCISCO CA | H11: 94103 | I11: UNITED STATES | J11: '320250140261791654' | K11: Business Services-Office Supplies | L11: AMEXPLATINUM | M11: =VLOOKUP(SUBSTITUTE(J11,"'",""),Sheet1!L:M,2,FALSE) -> 54820
A12: 45671 | B12: LEMONADE INSURANCE 5INTERNET NY | C12: 50.67 | D12: O8LQZO01079 HELP@LEMONADE.COM LEMONADE INSURANCE 529657 INTERNET NY HELP@LEMONADE.COM | E12: LEMONADE INSURANCE 5INTERNET NY | F12: 5 CROSBY ST FL 3 | G12: NEW YORK NY | H12: 10013 | I12: UNITED STATES | J12: '320250140262399923' | K12: Business Services-Insurance Services | L12: AMEXPLATINUM | M12: =VLOOKUP(SUBSTITUTE(J12,"'",""),Sheet1!L:M,2,FALSE) -> 54820
A13: 45671 | B13: FACTOR75 BATAVIA IL | C13: 65.36 | D13: MR029139295 18885735727 FACTOR75 BATAVIA IL 18885735727 | E13: FACTOR75 BATAVIA IL | F13: 1853 SUNCAST LN | G13: BATAVIA IL | H13: 60510 | I13: UNITED STATES | J13: '320250140265806913' | K13: Merchandise & Supplies-Groceries | L13: AMEXPLATINUM | M13: =VLOOKUP(SUBSTITUTE(J13,"'",""),Sheet1!L:M,2,FALSE) -> 54820
A14: 45671 | B14: FACTOR75 BATAVIA IL | C14: 29.99 | D14: MR029139306 18885735727 FACTOR75 BATAVIA IL 18885735727 | E14: FACTOR75 BATAVIA IL | F14: 1853 SUNCAST LN | G14: BATAVIA IL | H14: 60510 | I14: UNITED STATES | J14: '320250140266087960' | K14: Merchandise & Supplies-Groceries | L14: AMEXPLATINUM | M14: =VLOOKUP(SUBSTITUTE(J14,"'",""),Sheet1!L:M,2,FALSE) -> 54820
A15: 45671 | B15: AT&T | C15: 104.33 | D15: 48255058 800-331-0500 AT&T MOBILITY RECURRING 800-288-2020 TX Description : TELECOMMUNICATIONS Price : 0.00 800-331-0500 | E15: AT&T MOBILITY RECURR800-288-2020 TX | F15: 208 SOUTH AKARD ST FL 10 | G15: DALLAS TX | H15: 75202-4208 | I15: UNITED STATES | J15: '320250150296821107' | K15: Communications-Mobile Telecom | L15: DELTARESERVE | M15: =VLOOKUP(SUBSTITUTE(J15,"'",""),Sheet1!L:M,2,FALSE) -> 65700
A16: 45672 | B16: TST* ELIS NIGHTSHIFTNEW YORK NY | C16: 20.9 | D16: 21105175016 RESTAURANT TST* ELIS NIGHTSHIFT 00055845 NEW YORK NY RESTAURANT | E16: TST* ELIS NIGHTSHIFTNEW YORK NY | F16: 1390 THIRD AVE | G16: NEW YORK NY | H16: 10075 | I16: UNITED STATES | J16: '320250160319748672' | K16: Restaurant-Restaurant | L16: AMEXPLATINUM | M16: =VLOOKUP(SUBSTITUTE(J16,"'",""),Sheet1!L:M,2,FALSE) -> 54820
A17: 45672 | B17: TST* ELIS NIGHTSHIFTNEW YORK NY | C17: 20.9 | D17: 21105175016 RESTAURANT TST* ELIS NIGHTSHIFT 00055845 NEW YORK NY RESTAURANT | E17: TST* ELIS NIGHTSHIFTNEW YORK NY | F17: 1390 THIRD AVE | G17: NEW YORK NY | H17: 10075 | I17: UNITED STATES | J17: '320250160319791823' | K17: Restaurant-Restaurant | L17: AMEXPLATINUM | M17: =VLOOKUP(SUBSTITUTE(J17,"'",""),Sheet1!L:M,2,FALSE) -> 54820
A18: 45672 | B18: TABULAR EDITOR APS COPENHAGEN V DK | C18: 10 | D18: NT_RASZWGMX +4553503099 TABULAR EDITOR APS COPENHAGEN V DK +4553503099 | E18: TABULAR EDITOR APS COPENHAGEN V DK | F18: SUNDKAJ 125 NORDHAVN | H18: 2150 | I18: DENMARK | J18: '320250160323251142' | K18: Merchandise & Supplies-Computer Supplies | L18: DELTARESERVE | M18: =VLOOKUP(SUBSTITUTE(J18,"'",""),Sheet1!L:M,2,FALSE) -> 64100
A19: 45673 | B19: SPLICE.COM NEW YORK CITY NY | C19: 27.99 | D19: NT_RB8R0ADK 3235775423 SPLICE.COM NEW YORK CITY NY 3235775423 | E19: SPLICE.COM NEW YORK CITY NY | F19: 817 BROADWAY 4TH FLOOR | G19: NEW YORK NY | H19: 10003 | I19: UNITED STATES | J19: '320250160313491858' | K19: Merchandise & Supplies-Computer Supplies | L19: AMEXPLATINUM | M19: =VLOOKUP(SUBSTITUTE(J19,"'",""),Sheet1!L:M,2,FALSE) -> 54820
A20: 45673 | B20: UBER EATS help.uber.com CA | C20: 91.19 | D20: 9V9NGXPX 5Z7BARTO 94103 UBER EATS help.uber.com CA 5Z7BARTO 94103 | E20: UBER EATS help.uber.com CA | F20: 1455 MARKET ST - | G20: SAN FRANCISCO CA | H20: 94103 | I20: UNITED STATES | J20: '320250160316131282' | K20: Restaurant-Restaurant | L20: DELTARESERVE | M20: =VLOOKUP(SUBSTITUTE(J20,"'",""),Sheet1!L:M,2,FALSE) -> 54820
A21: 45673 | B21: UPWORK SAN FRANCISCO | C21: 378.72 | D21: T771017188 11376536 12866 INVOICE CHARGE UPWORK SAN FRANCISCO INVOICE CHARGE 11376536 12866 | E21: UPWORK SAN FRANCISCO | F21: 475 BRANNAN ST SUITE 430 | G21: SAN FRANCISCO CA | H21: 94107 | I21: UNITED STATES | J21: '320250160329171458' | K21: Other-Miscellaneous | L21: DELTARESERVE | M21: =VLOOKUP(SUBSTITUTE(J21,"'",""),Sheet1!L:M,2,FALSE) -> 64200
A22: 45673 | B22: WEGMANS ASTOR PLACE NEW YORK NY | C22: 49.57 | D22: W15639500475854293656 WEGMANS ASTOR PLACE 156 000000156 NEW YORK NY 5854293656 | E22: WEGMANS ASTOR PLACE NEW YORK NY | F22: 770 BROADWAY | G22: NEW YORK NY | H22: 10003 | I22: UNITED STATES | J22: '320250170349399169' | K22: Merchandise & Supplies-Groceries | L22: AMEXPLATINUM | M22: =VLOOKUP(SUBSTITUTE(J22,"'",""),Sheet1!L:M,2,FALSE) -> 54820
A23: 45673 | B23: KALL8 08487000633357SEATTLE WA | C23: 15.41 | D23: 004317822624317822629 981191 KALL8 084870006333577 SEATTLE WA 4317822629 981191 | E23: KALL8 08487000633357SEATTLE WA | F23: 417 2ND AVE WEST | G23: SEATTLE WA | H23: 98119 | I23: UNITED STATES | J23: '320250180384383438' | K23: Other-Miscellaneous | L23: AMEXPLATINUM | M23: =VLOOKUP(SUBSTITUTE(J23,"'",""),Sheet1!L:M,2,FALSE) -> 65700
A24: 45674 | B24: CVS PHARMACY NEW YORK NY | C24: 16.83 | D24: 10186013 8007467287 CVS PHARMACY NEW YORK NY Description : PHARMACIES Price : 0.1683 8007467287 | E24: CVS PHARMACY NEW YORK NY | F24: 158 BLEECKER ST | G24: NEW YORK NY | H24: 10012 | I24: UNITED STATES | J24: '320250180376610675' | K24: Merchandise & Supplies-Pharmacies | L24: AMEXPLATINUM | M24: =VLOOKUP(SUBSTITUTE(J24,"'",""),Sheet1!L:M,2,FALSE) -> 54820
A25: 45675 | B25: DUOLINGO PLUS 12 MONPITTSBURGH PA | C25: 83.99 | D25: NT_RBUH16VJ +14125676602 DUOLINGO PLUS 12 MONTH PITTSBURGH PA +14125676602 | E25: DUOLINGO PLUS 12 MONPITTSBURGH PA | F25: 5900 PENN AVE | G25: PITTSBURGH PA | H25: 15206 | I25: UNITED STATES | J25: '320250180364632138' | K25: Other-Education | L25: AMEXPLATINUM | M25: =VLOOKUP(SUBSTITUTE(J25,"'",""),Sheet1!L:M,2,FALSE) -> 54820
A26: 45675 | B26: PETCO.COM 6989 0698 SAN DIEGO CA | C26: 61.75 | D26: 14888690559 858-453-7845 PETCO.COM 6989 0698 SAN DIEGO CA Description : PETS/SUPPLIES/ACC Price : 0.00 858-453-7845 | E26: PETCO.COM 6989 0698 SAN DIEGO CA | F26: 10850 VIA FRONTERA | G26: SAN DIEGO CA | H26: 92127 | I26: UNITED STATES | J26: '320250190401162038' | K26: Merchandise & Supplies-Internet Purchase | L26: AMEXPLATINUM | M26: =VLOOKUP(SUBSTITUTE(J26,"'",""),Sheet1!L:M,2,FALSE) -> 54820
A27: 45675 | B27: EXXONMOBIL 9736 HANNACROIX NY | C27: 43.18 | D27: 00203155 518-756-9700 EXXONMOBIL 9736 HANNACROIX NY Description : 001 Price : 0.00 518-756-9700 | E27: EXXONMOBIL 9736 HANNACROIX NY | F27: - | G27: (800) 243-9966 TX | H27: 77389 | I27: UNITED STATES | J27: '320250190405707295' | K27: Transportation-Fuel | L27: DELTARESERVE | M27: =VLOOKUP(SUBSTITUTE(J27,"'",""),Sheet1!L:M,2,FALSE) -> 63100
A28: 45676 | B28: UNIQLO 5TH AVE NEW YORK NY | C28: 124.3 | D28: C91BEB35-44 FAMILY CLOTHING UNIQLO 5TH AVE NEW YORK NY FAMILY CLOTHING | E28: UNIQLO 5TH AVE NEW YORK NY | F28: 666 5TH AVE FRNT 9 | G28: NEW YORK NY | H28: 10103-0029 | I28: UNITED STATES | J28: '320250190391173789' | K28: Merchandise & Supplies-Clothing Stores | L28: AMEXPLATINUM | M28: =VLOOKUP(SUBSTITUTE(J28,"'",""),Sheet1!L:M,2,FALSE) -> 54820
A29: 45676 | B29: BANANAREPUBLIC US 63NEW YORK NY | C29: 608.6 | D29: 805254 0000000000000000010003 BANANAREPUBLIC US 63 NEW YORK NY 0000000000000000010003 | E29: BANANAREPUBLIC US 63NEW YORK NY | F29: 105 5TH AVE | G29: NEW YORK NY | H29: 10003 | I29: UNITED STATES | J29: '320250200427753786' | K29: Merchandise & Supplies-Clothing Stores | L29: AMEXPLATINUM | M29: =VLOOKUP(SUBSTITUTE(J29,"'",""),Sheet1!L:M,2,FALSE) -> 54820
A30: 45676 | B30: SKYPE LUXEMBOURG | C30: 29.94 | D30: 80640000067 TELECOM SERVICE SKYPE LUXEMBOURG TELECOM SERVICE | E30: SKYPE LUXEMBOURG | F30: SUBMISSIONS USD | G30: USA 000 | H30: 00000 | I30: UNITED STATES | J30: '320250210446082211' | K30: Communications-Telephone Comm | L30: DELTARESERVE | M30: =VLOOKUP(SUBSTITUTE(J30,"'",""),Sheet1!L:M,2,FALSE) -> 64100
A31: 45677 | B31: THE CLEANERS IO, LLCNew York NY | C31: 46.9 | D31: BcgpcW8E9jl squareup.com/receipts THE CLEANERS IO, LLC New York NY squareup.com/receipts | E31: THE CLEANERS IO, LLCNew York NY | F31: 215 THOMPSON ST | G31: NEW YORK NY | H31: 10012 | I31: UNITED STATES | J31: '320250200417808285' | K31: Business Services-Other Services | L31: AMEXPLATINUM | M31: =VLOOKUP(SUBSTITUTE(J31,"'",""),Sheet1!L:M,2,FALSE) -> 67500
A32: 45677 | B32: SPLICE.COM NEW YORK CITY NY | C32: 8.55 | D32: NT_RCBM9V3Z 3235775423 SPLICE.COM NEW YORK CITY NY 3235775423 | E32: SPLICE.COM NEW YORK CITY NY | F32: 817 BROADWAY FLOOR 4 | G32: NEW YORK NY | H32: 10003 | I32: UNITED STATES | J32: '320250200420302666' | K32: Merchandise & Supplies-Computer Supplies | L32: AMEXPLATINUM | M32: =VLOOKUP(SUBSTITUTE(J32,"'",""),Sheet1!L:M,2,FALSE) -> 54820
A33: 45677 | B33: UBER | C33: 41.72 | D33: HNKFEPZ5 WPCCSLXW 10012 Uber Trip help.uber.com CA WPCCSLXW 10012 | E33: Uber Trip help.uber.com CA | F33: 1455 MARKET ST 4TH FLOOR | G33: SAN FRANCISCO CA | H33: 94103 | I33: UNITED STATES | J33: '320250200421677863' | K33: Transportation-Taxis & Coach | L33: DELTARESERVE | M33: =VLOOKUP(SUBSTITUTE(J33,"'",""),Sheet1!L:M,2,FALSE) -> 61130
A34: 45677 | B34: UBER | C34: 35.67 | D34: JGV2DHJ2 TLT27AVX 10022 Uber Trip help.uber.com CA TLT27AVX 10022 | E34: Uber Trip help.uber.com CA | F34: 1455 MARKET ST 4TH FLOOR | G34: SAN FRANCISCO CA | H34: 94103 | I34: UNITED STATES | J34: '320250200421938841' | K34: Transportation-Taxis & Coach | L34: DELTARESERVE | M34: =VLOOKUP(SUBSTITUTE(J34,"'",""),Sheet1!L:M,2,FALSE) -> 61130
A35: 45677 | B35: NYS THRUWAY AUTO REPSTATEN ISLAND NY | C35: 30 | D35: 1P-83240939 TOLL & BRIDGE FEE NYS THRUWAY AUTO REPLEN STATEN ISLAND NY Description : FOR BILLING QUESTIO Price : 0.00 Description : ACCT: 1P-832409396 Price : 0.00 TOLL & BRIDGE FEE | E35: NYS THRUWAY AUTO REPSTATEN ISLAND NY | F35: 1 EDGEWATER ST STE 308 | G35: STATEN ISLAND NY | H35: 10305-4900 | I35: UNITED STATES | J35: '320250200422515828' | K35: Transportation-Tolls & Fees | L35: AMEXPLATINUM | M35: =VLOOKUP(SUBSTITUTE(J35,"'",""),Sheet1!L:M,2,FALSE) -> 61131
A36: 45677 | B36: FACTOR75 BATAVIA IL | C36: -29.99 | D36: MR029139306 18885735727 FACTOR75 BATAVIA IL 18885735727 | E36: FACTOR75 BATAVIA IL | F36: 1853 SUNCAST LN | G36: BATAVIA IL | H36: 60510 | I36: UNITED STATES | J36: '320250210445601194' | K36: Merchandise & Supplies-Groceries | L36: AMEXPLATINUM | M36: =VLOOKUP(SUBSTITUTE(J36,"'",""),Sheet1!L:M,2,FALSE) -> 54820
A37: 45677 | B37: FACTOR75 BATAVIA IL | C37: -65.36 | D37: MR029139295 18885735727 FACTOR75 BATAVIA IL 18885735727 | E37: FACTOR75 BATAVIA IL | F37: 1853 SUNCAST LN | G37: BATAVIA IL | H37: 60510 | I37: UNITED STATES | J37: '320250210445619784' | K37: Merchandise & Supplies-Groceries | L37: AMEXPLATINUM | M37: =VLOOKUP(SUBSTITUTE(J37,"'",""),Sheet1!L:M,2,FALSE) -> 54820
A38: 45677 | B38: MS* MAKEMESURPRISE WALNUT CA | C38: 37.83 | D38: NT_RCNPN8QZ 8332226883 MS* MAKEMESURPRISE WALNUT CA 8332226883 | E38: MS* MAKEMESURPRISE WALNUT CA | F38: 340 SOUTH LEMON AVE 3159 | G38: WALNUT CA | H38: 91789 | I38: UNITED STATES | J38: '320250210451773828' | K38: Merchandise & Supplies-Clothing Stores | L38: AMEXPLATINUM | M38: =VLOOKUP(SUBSTITUTE(J38,"'",""),Sheet1!L:M,2,FALSE) -> 54820
A39: 45677 | B39: EXXONMOBIL 9736 MALDEN ON HUD NY | C39: 38.94 | D39: 00704358 845-246-3510 EXXONMOBIL 9736 MALDEN ON HUD NY Description : 001 Price : 0.00 845-246-3510 | E39: EXXONMOBIL 9736 MALDEN ON HUD NY | F39: - | G39: (800) 243-9966 TX | H39: 77389 | I39: UNITED STATES | J39: '320250210453229075' | K39: Transportation-Fuel | L39: DELTARESERVE | M39: =VLOOKUP(SUBSTITUTE(J39,"'",""),Sheet1!L:M,2,FALSE) -> 63100
A40: 45678 | B40: ONLINE PAYMENT - THANK YOU | C40: -3000 | D40: ONLINE PAYMENT - THANK YOU | E40: ONLINE PAYMENT - THANK YOU | J40: '320250210436627702' | L40: AMEXPLATINUM | M40: =VLOOKUP(SUBSTITUTE(J40,"'",""),Sheet1!L:M,2,FALSE) -> #N/A
A41: 45678 | B41: ONLINE PAYMENT - THANK YOU | C41: -3000 | D41: ONLINE PAYMENT - THANK YOU | E41: ONLINE PAYMENT - THANK YOU | J41: '320250210436633632' | L41: AMEXPLATINUM | M41: =VLOOKUP(SUBSTITUTE(J41,"'",""),Sheet1!L:M,2,FALSE) -> #N/A
A42: 45678 | B42: FACTOR75 BATAVIA IL | C42: 65.36 | D42: MR029149442 18885735727 FACTOR75 BATAVIA IL 18885735727 | E42: FACTOR75 BATAVIA IL | F42: 1853 SUNCAST LN | G42: BATAVIA IL | H42: 60510 | I42: UNITED STATES | J42: '320250210444525546' | K42: Merchandise & Supplies-Groceries | L42: AMEXPLATINUM | M42: =VLOOKUP(SUBSTITUTE(J42,"'",""),Sheet1!L:M,2,FALSE) -> 54820
A43: 45679 | B43: ROVEN LAW GROUP PC NEW YORK CITY NY | C43: 2500 | D43: ######NB63Z PROFESSIONAL SERVICE ROVEN LAW GROUP PC NEW YORK CITY NY PROFESSIONAL SERVICE | E43: ROVEN LAW GROUP PC NEW YORK CITY NY | F43: 3 PARK AVE | G43: NEW YORK NY | H43: 10016 | I43: UNITED STATES | J43: '320250220480065707' | K43: Business Services-Professional Services | L43: DELTARESERVE | M43: =VLOOKUP(SUBSTITUTE(J43,"'",""),Sheet1!L:M,2,FALSE) -> 65505
A44: 45679 | B44: OPENAI *CHATGPT SUBSSAN FRANCISCO CA | C44: 21.4 | D44: NT_RDLGEZO3 +14158799686 OPENAI *CHATGPT SUBSCR SAN FRANCISCO CA +14158799686 | E44: OPENAI *CHATGPT SUBSSAN FRANCISCO CA | F44: 3180 18TH ST STE 100 | G44: SAN FRANCISCO CA | H44: 94110 | I44: UNITED STATES | J44: '320250220480226117' | K44: Merchandise & Supplies-Computer Supplies | L44: DELTARESERVE | M44: =VLOOKUP(SUBSTITUTE(J44,"'",""),Sheet1!L:M,2,FALSE) -> 64100
A45: 45679 | B45: UBER | C45: 29.62 | D45: 9J0EPAKN YD5EE3PO 12866 Uber Trip help.uber.com CA YD5EE3PO 12866 | E45: Uber Trip help.uber.com CA | F45: 1455 MARKET ST 4TH FLOOR | G45: SAN FRANCISCO CA | H45: 94103 | I45: UNITED STATES | J45: '320250220480875757' | K45: Transportation-Taxis & Coach | L45: DELTARESERVE | M45: =VLOOKUP(SUBSTITUTE(J45,"'",""),Sheet1!L:M,2,FALSE) -> 61130
A46: 45680 | B46: SPO*PANZA'SRESTAURANSARATOGA SPRI NY | C46: 320 | D46: 99999995023 5185846882 SPO*PANZA'SRESTAURANT 000001432 SARATOGA SPRI NY 5185846882 | E46: SPO*PANZA'SRESTAURANSARATOGA SPRI NY | F46: 129 SOUTH BROADWAY | G46: SARATOGA SPRINGS NY | H46: 12866-4532 | I46: UNITED STATES | J46: '320250230494615493' | K46: Restaurant-Restaurant | L46: DELTARESERVE | M46: =VLOOKUP(SUBSTITUTE(J46,"'",""),Sheet1!L:M,2,FALSE) -> 61215
A47: 45680 | B47: CVS/PHARMACY #10612 MANHATTAN NY | C47: 29.64 | D47: 10084051 8007467287 PHARMACIES CVS/PHARMACY #10612 000010612 MANHATTAN NY PHARMACIES 8007467287 | E47: CVS/PHARMACY #10612 MANHATTAN NY | F47: 5TH AVE 14TH ST SEC | G47: MANHATTAN NY | H47: 10011 | I47: UNITED STATES | J47: '320250240521906081' | K47: Merchandise & Supplies-Pharmacies | L47: AMEXPLATINUM | M47: =VLOOKUP(SUBSTITUTE(J47,"'",""),Sheet1!L:M,2,FALSE) -> 54820
A48: 45681 | B48: GABRIEL KRREUTHER NEW YORK NY | C48: 816.56 | D48: NT_REAKIWYY +12122575826 GABRIEL KRREUTHER NEW YORK NY +12122575826 | E48: GABRIEL KRREUTHER NEW YORK NY | F48: 1114 6TH AVE | G48: NEW YORK NY | H48: 10036 | I48: UNITED STATES | J48: '320250240532351565' | K48: Restaurant-Restaurant | L48: DELTARESERVE | M48: =VLOOKUP(SUBSTITUTE(J48,"'",""),Sheet1!L:M,2,FALSE) -> 61215
A49: 45681 | B49: CVS PHARMACY NEW YORK NY | C49: 99.96 | D49: 10176850 8007467287 PHARMACIES CVS PHARMACY NEW YORK NY PHARMACIES 8007467287 | E49: CVS PHARMACY NEW YORK NY | F49: 158 BLEECKER ST | G49: NEW YORK NY | H49: 10012 | I49: UNITED STATES | J49: '320250250546960411' | K49: Merchandise & Supplies-Pharmacies | L49: AMEXPLATINUM | M49: =VLOOKUP(SUBSTITUTE(J49,"'",""),Sheet1!L:M,2,FALSE) -> 54820
A50: 45681 | B50: SUNOCO 0528522600 05SARATOGA SPRI NY | C50: 43.68 | D50: 00122285 518-584-5380 SUNOCO 0528522600 0528 SARATOGA SPRI NY Description : Unleaded Plus (89 - Price : 0.00 518-584-5380 | E50: SUNOCO 0528522600 05SARATOGA SPRI NY | F50: - | G50: =- TX -> #NAME? | H50: 75231 | I50: UNITED STATES | J50: '320250250550225576' | K50: Transportation-Fuel | L50: DELTARESERVE | M50: =VLOOKUP(SUBSTITUTE(J50,"'",""),Sheet1!L:M,2,FALSE) -> 63100
A51: 45681 | B51: TMPL ASTOR PLACE 000NEW YORK NY | C51: 1045 | D51: 62300010 917-877-1400 TMPL ASTOR PLACE 0000 NEW YORK NY Description : MEMBERSHIP FEES Price : 0.00 917-877-1400 | E51: TMPL ASTOR PLACE 000NEW YORK NY | F51: 4 ASTOR PLACE | G51: NEW YORK NY | H51: 10003 | I51: UNITED STATES | J51: '320250250551476778' | K51: Entertainment-Associations | L51: AMEXPLATINUM | M51: =VLOOKUP(SUBSTITUTE(J51,"'",""),Sheet1!L:M,2,FALSE) -> 54820
A52: 45681 | B52: KIMBERLY MEEHAN, NP NEW YORK NY | C52: 200 | D52: 73011005024DDC1F4EA497C4284910017 KIMBERLY MEEHAN, NP IN PS 316107142119 NEW YORK NY DDC1F4EA497C4284910017 | E52: KIMBERLY MEEHAN, NP NEW YORK NY | F52: 18 EAST 41ST ST 14TH FLOOR | G52: NEW YORK NY | H52: 10017 | I52: UNITED STATES | J52: '320250250557996171' | K52: Business Services-Health Care Services | L52: AMEXPLATINUM | M52: =VLOOKUP(SUBSTITUTE(J52,"'",""),Sheet1!L:M,2,FALSE) -> 54820
A53: 45682 | B53: WEGMANS ASTOR PLACE NEW YORK NY | C53: 152.76 | D53: W15608700875854293656 WEGMANS ASTOR PLACE 156 000000156 NEW YORK NY 5854293656 | E53: WEGMANS ASTOR PLACE NEW YORK NY | F53: 770 BROADWAY | G53: NEW YORK NY | H53: 10003 | I53: UNITED STATES | J53: '320250260574267348' | K53: Merchandise & Supplies-Groceries | L53: AMEXPLATINUM | M53: =VLOOKUP(SUBSTITUTE(J53,"'",""),Sheet1!L:M,2,FALSE) -> 54820
A54: 45682 | B54: STEWARTS ICE CREAM SARATOGA SPRINGS NY | C54: 35.62 | D54: 00251700027 5185811201 STEWARTS ICE CREAM SARATOGA SPRINGS NY Description : AUTOMATED FUEL Price : 0.3562 5185811201 | E54: STEWARTS ICE CREAM SARATOGA SPRINGS NY | F54: 402 LK AVE | G54: SARATOGA SPRINGS NY | H54: 12866 | I54: UNITED STATES | J54: '320250260574579021' | K54: Transportation-Fuel | L54: DELTARESERVE | M54: =VLOOKUP(SUBSTITUTE(J54,"'",""),Sheet1!L:M,2,FALSE) -> 63100
A55: 45683 | B55: ONLINE PAYMENT - THANK YOU | C55: -21000 | D55: ONLINE PAYMENT - THANK YOU | E55: ONLINE PAYMENT - THANK YOU | J55: '320250260559537067' | L55: AMEXPLATINUM | M55: =VLOOKUP(SUBSTITUTE(J55,"'",""),Sheet1!L:M,2,FALSE) -> #N/A
A56: 45683 | B56: AMAZON MUSIC*ZG0OJ35888-802-3080 WA | C56: 9.99 | D56: 3HYAPU9BQF9 DIGITAL AMAZON MUSIC*ZG0OJ3561 888-802-3080 WA DIGITAL | E56: AMAZON MUSIC*ZG0OJ35888-802-3080 WA | F56: 1512 2ND AVE | G56: SEATTLE WA | H56: 98101-1508 | I56: UNITED STATES | J56: '320250260566406754' | K56: Merchandise & Supplies-Internet Purchase | L56: DELTARESERVE | M56: =VLOOKUP(SUBSTITUTE(J56,"'",""),Sheet1!L:M,2,FALSE) -> 54820
A57: 45683 | B57: ENTERPRISE 023893SARATOGA SPRI NY | C57: 338.76 | D57: 018653145 518-5870687 ENTERPRISE 023893 01810023893 SARATOGA SPRI NY | E57: ENTERPRISE 023893SARATOGA SPRI NY | F57: 182 SOUTH BROADWAY | G57: SARATOGA SPRINGS NY | H57: 12866 | I57: UNITED STATES | J57: '320250270602570267' | K57: Travel-Vehicle Rental | L57: DELTARESERVE | M57: =VLOOKUP(SUBSTITUTE(J57,"'",""),Sheet1!L:M,2,FALSE) -> 61131
A58: 45683 | B58: CALENDLY AVONDALE ESTATES GA | C58: 16.05 | D58: NT_RF120UU3 +18009799850 CALENDLY AVONDALE ESTATES GA +18009799850 | E58: CALENDLY AVONDALE ESTATES GA | F58: "140 NEW MONTGOMERY, FLOOR 2" | G58: SAN FRANCISCO CA | H58: 94105 | I58: UNITED STATES | J58: '320250270603776701' | K58: Merchandise & Supplies-Computer Supplies | L58: AMEXPLATINUM | M58: =VLOOKUP(SUBSTITUTE(J58,"'",""),Sheet1!L:M,2,FALSE) -> 64100
A59: 45685 | B59: FACTOR75 NEW YORK NY | C59: 65.36 | D59: GJCZQSKZ 18885735727 FACTOR75 NEW YORK NY 18885735727 | E59: FACTOR75 NEW YORK NY | F59: 1853 SUNCAST LN | G59: BATAVIA IL | H59: 60510 | I59: UNITED STATES | J59: '320250280617583780' | K59: Merchandise & Supplies-Groceries | L59: AMEXPLATINUM | M59: =VLOOKUP(SUBSTITUTE(J59,"'",""),Sheet1!L:M,2,FALSE) -> 54820
A60: 45685 | B60: PREM CAR RENTAL PROTECTION 800-326-2078 | C60: 24.95 | D60: CRA018653145 01/25/2025 SARATOGA SPRINGS PREM CAR RENTAL PROTECTION 800-326-2078 | E60: PREM CAR RENTAL PROTECTION 800-326-2078 | F60: 200 VESEY STREET 43RD FLOOR | G60: NEW YORK NY | H60: 10285 | I60: UNITED STATES | J60: '320250280631442372' | K60: Business Services-Insurance Services | L60: DELTARESERVE | M60: =VLOOKUP(SUBSTITUTE(J60,"'",""),Sheet1!L:M,2,FALSE) -> 61131
A61: 45685 | B61: CVS/PHARMACY #10612 MANHATTAN NY | C61: 56.82 | D61: 10085463 8007467287 CVS/PHARMACY #10612 000010612 MANHATTAN NY Description : PHARMACIES Price : 0.5682 8007467287 | E61: CVS/PHARMACY #10612 MANHATTAN NY | F61: 5TH AVE 14TH ST SEC | G61: MANHATTAN NY | H61: 10011 | I61: UNITED STATES | J61: '320250290648209204' | K61: Merchandise & Supplies-Pharmacies | L61: AMEXPLATINUM | M61: =VLOOKUP(SUBSTITUTE(J61,"'",""),Sheet1!L:M,2,FALSE) -> 54820
A62: 45685 | B62: TST* HUDSON YARDS - NEW YORK NY | C62: 22.3 | D62: 99999995028 3472848291 TST* HUDSON YARDS - ANA'S 300579326 NEW YORK NY Description : RESTAURANTS Price : 0.223 3472848291 | E62: TST* HUDSON YARDS - NEW YORK NY | F62: 40 752861 74 000838 2ND FL | G62: NEW YORK NY | H62: 10001 | I62: UNITED STATES | J62: '320250290654632618' | K62: Restaurant-Restaurant | L62: DELTARESERVE | M62: =VLOOKUP(SUBSTITUTE(J62,"'",""),Sheet1!L:M,2,FALSE) -> 61215
A63: 45686 | B63: UBER | C63: 31.2 | D63: 96Z0RAHG O6NIT7BG 10001 Uber Trip help.uber.com CA O6NIT7BG 10001 | E63: Uber Trip help.uber.com CA | F63: 1455 MARKET ST 4TH FLOOR | G63: SAN FRANCISCO CA | H63: 94103 | I63: UNITED STATES | J63: '320250290642540993' | K63: Transportation-Taxis & Coach | L63: DELTARESERVE | M63: =VLOOKUP(SUBSTITUTE(J63,"'",""),Sheet1!L:M,2,FALSE) -> 61130
A64: 45686 | B64: KIMBERLY MEEHAN, NP NEW YORK NY | C64: 200 | D64: 73011005029DDC1F4EA497C4284910017 KIMBERLY MEEHAN, NP IN PS 316107142119 NEW YORK NY DDC1F4EA497C4284910017 | E64: KIMBERLY MEEHAN, NP NEW YORK NY | F64: 18 EAST 41ST ST 14TH FLOOR | G64: NEW YORK NY | H64: 10017 | I64: UNITED STATES | J64: '320250300680573298' | K64: Business Services-Health Care Services | L64: AMEXPLATINUM | M64: =VLOOKUP(SUBSTITUTE(J64,"'",""),Sheet1!L:M,2,FALSE) -> 54820
A65: 45687 | B65: UPWORK SAN FRANCISCO | C65: 29.99 | D65: T775355857 11376536 12866 INVOICE CHARGE UPWORK SAN FRANCISCO INVOICE CHARGE 11376536 12866 | E65: UPWORK SAN FRANCISCO | F65: 475 BRANNAN ST SUITE 430 | G65: SAN FRANCISCO CA | H65: 94107 | I65: UNITED STATES | J65: '320250300664569912' | K65: Other-Miscellaneous | L65: DELTARESERVE | M65: =VLOOKUP(SUBSTITUTE(J65,"'",""),Sheet1!L:M,2,FALSE) -> 64200
A66: 45687 | B66: THE CLEANERS IO, LLCNew York NY | C66: 42.88 | D66: VUV8agaHtcy squareup.com/receipts THE CLEANERS IO, LLC New York NY squareup.com/receipts | E66: THE CLEANERS IO, LLCNew York NY | F66: 215 THOMPSON ST | G66: NEW YORK NY | H66: 10012 | I66: UNITED STATES | J66: '320250300666501005' | K66: Business Services-Other Services | L66: AMEXPLATINUM | M66: =VLOOKUP(SUBSTITUTE(J66,"'",""),Sheet1!L:M,2,FALSE) -> 67500
A67: 45687 | B67: NYS THRUWAY AUTO REPSTATEN ISLAND NY | C67: 30 | D67: 1P-83482884 TOLL & BRIDGE FEE NYS THRUWAY AUTO REPLEN STATEN ISLAND NY Description : FOR BILLING QUESTIO Price : 0.00 Description : ACCT: 1P-834828845 Price : 0.00 TOLL & BRIDGE FEE | E67: NYS THRUWAY AUTO REPSTATEN ISLAND NY | F67: 1 EDGEWATER ST STE 308 | G67: STATEN ISLAND NY | H67: 10305-4900 | I67: UNITED STATES | J67: '320250300667809353' | K67: Transportation-Tolls & Fees | L67: AMEXPLATINUM | M67: =VLOOKUP(SUBSTITUTE(J67,"'",""),Sheet1!L:M,2,FALSE) -> 61131
A68: 45687 | B68: UBER | C68: 51.51 | D68: 3HBPPC49 4N5HBCBH 10004 Uber Trip help.uber.com CA 4N5HBCBH 10004 | E68: Uber Trip help.uber.com CA | F68: 1455 MARKET ST 4TH FLOOR | G68: SAN FRANCISCO CA | H68: 94103 | I68: UNITED STATES | J68: '320250300668533536' | K68: Transportation-Taxis & Coach | L68: DELTARESERVE | M68: =VLOOKUP(SUBSTITUTE(J68,"'",""),Sheet1!L:M,2,FALSE) -> 61130
A69: 45687 | B69: PETCO 3741 0374 NEW YORK NY | C69: 112.98 | D69: 34600063 858-453-7845 PETCO 3741 0374 NEW YORK NY Description : PETS/SUPPLIES/ACC Price : 0.00 858-453-7845 | E69: PETCO 3741 0374 NEW YORK NY | F69: 44 UN SQ EAST | G69: NEW YORK NY | H69: 10003 | I69: UNITED STATES | J69: '320250310697436680' | K69: Merchandise & Supplies-General Retail | L69: AMEXPLATINUM | M69: =VLOOKUP(SUBSTITUTE(J69,"'",""),Sheet1!L:M,2,FALSE) -> 54820
A70: 45688 | B70: TST* FRENCHETTE RESTNEW YORK NY | C70: 541 | D70: 00143306022 RESTAURANT TST* FRENCHETTE RESTAURAN 00143306 NEW YORK NY RESTAURANT | E70: TST* FRENCHETTE RESTNEW YORK NY | F70: 241 WEST BROADWAY | G70: NEW YORK NY | H70: 10013 | I70: UNITED STATES | J70: '320250320729532597' | K70: Restaurant-Restaurant | L70: DELTARESERVE | M70: =VLOOKUP(SUBSTITUTE(J70,"'",""),Sheet1!L:M,2,FALSE) -> 61215
A71: 45689 | B71: UBER | C71: 28.96 | D71: M031X7BB VMSBAG74 10013 Uber Trip help.uber.com CA VMSBAG74 10013 | E71: Uber Trip help.uber.com CA | F71: 1455 MARKET ST 4TH FLOOR | G71: SAN FRANCISCO CA | H71: 94103 | I71: UNITED STATES | J71: '320250320718728174' | K71: Transportation-Taxis & Coach | L71: DELTARESERVE | M71: =VLOOKUP(SUBSTITUTE(J71,"'",""),Sheet1!L:M,2,FALSE) -> 61130
A72: 45689 | B72: VERIZON WRLS RCCRNG PMTS | C72: 223.34 | D72: N0000003872VZWRLSS*APOCC VZW APO 800-922-0204 FL VZWRLSS*APOCC | E72: VZW APO 800-922-0204 FL | F72: 600 COOLIDGE DR | G72: FOLSOM CA | H72: 95630-3155 | I72: UNITED STATES | J72: '320250320725416327' | K72: Communications-Mobile Telecom | L72: DELTARESERVE | M72: =VLOOKUP(SUBSTITUTE(J72,"'",""),Sheet1!L:M,2,FALSE) -> 65700
A73: 45689 | B73: Amazon Web Services AWS.Amazon.com WA | C73: 2067.61 | D73: 5N6ET1GOHLO WEB SERVICES Amazon Web Services AWS.Amazon.com WA WEB SERVICES | E73: Amazon Web Services AWS.Amazon.com WA | F73: 1512 2ND AVE | G73: SEATTLE WA | H73: 98101 | I73: UNITED STATES | J73: '320250330756886674' | K73: Merchandise & Supplies-Internet Purchase | L73: AMEXPLATINUM | M73: =VLOOKUP(SUBSTITUTE(J73,"'",""),Sheet1!L:M,2,FALSE) -> 64101
A74: 45690 | B74: UBER | C74: 83.98 | D74: GW8A7WFK WJMIFRYD 10012 Uber Trip help.uber.com CA WJMIFRYD 10012 | E74: Uber Trip help.uber.com CA | F74: 1455 MARKET ST 4TH FLOOR | G74: SAN FRANCISCO CA | H74: 94103 | I74: UNITED STATES | J74: '320250330744556782' | K74: Transportation-Taxis & Coach | L74: DELTARESERVE | M74: =VLOOKUP(SUBSTITUTE(J74,"'",""),Sheet1!L:M,2,FALSE) -> 61130
A75: 45690 | B75: UBER | C75: 62.63 | D75: 9Y9ZD05G EUJW3MYR 10028 Uber Trip help.uber.com CA EUJW3MYR 10028 | E75: Uber Trip help.uber.com CA | F75: 1455 MARKET ST 4TH FLOOR | G75: SAN FRANCISCO CA | H75: 94103 | I75: UNITED STATES | J75: '320250330745180767' | K75: Transportation-Taxis & Coach | L75: DELTARESERVE | M75: =VLOOKUP(SUBSTITUTE(J75,"'",""),Sheet1!L:M,2,FALSE) -> 61130
A76: 45690 | B76: ERACTOLL 71MMFD 877-860-1258 NY | C76: 23.75 | D76: T186468032 877-860-1258 ERACTOLL 71MMFD 877-860-1258 NY Description : ERACTOLL 71MMFD Price : 0.00 877-860-1258 | E76: ERACTOLL 71MMFD 877-860-1258 NY | F76: - | G76: =- NY -> #NAME? | H76: 11577 | I76: UNITED STATES | J76: '320250340774825564' | K76: Transportation-Tolls & Fees | L76: DELTARESERVE | M76: =VLOOKUP(SUBSTITUTE(J76,"'",""),Sheet1!L:M,2,FALSE) -> 61131
A77: 45690 | B77: ELECTRONIC ARTS INC.REDWOOD CITY CA | C77: 42.79 | D77: ######3qF9D DIGITAL GOODS: GAMES ELECTRONIC ARTS INC. REDWOOD CITY CA DIGITAL GOODS: GAMES | E77: ELECTRONIC ARTS INC.REDWOOD CITY CA | F77: 209 REDWOOD SHRS PKWY | G77: REDWOOD CITY CA | H77: 94065 | I77: UNITED STATES | J77: '320250340784943406' | K77: Business Services-Employment Agencies | L77: AMEXPLATINUM | M77: =VLOOKUP(SUBSTITUTE(J77,"'",""),Sheet1!L:M,2,FALSE) -> 54820
A78: 45691 | B78: UBER | C78: 27.68 | D78: CTQJZV62 GVSUYXOH 10012 Uber Trip help.uber.com CA GVSUYXOH 10012 | E78: Uber Trip help.uber.com CA | F78: 1455 MARKET ST 4TH FLOOR | G78: SAN FRANCISCO CA | H78: 94103 | I78: UNITED STATES | J78: '320250340770771156' | K78: Transportation-Taxis & Coach | L78: DELTARESERVE | M78: =VLOOKUP(SUBSTITUTE(J78,"'",""),Sheet1!L:M,2,FALSE) -> 61130
A79: 45691 | B79: CREDITSECURE CostaMesa CA | C79: 21.39 | D79: 103649195 1-866-617-1893 CREDITSECURE CostaMesa CA Description : $19.99+$1.40 NY TAX Price : 0.00 1-866-617-1893 | E79: CREDITSECURE CostaMesa CA | F79: 200 VESEY ST FL 7 | G79: NEW YORK NY | H79: 10019 | I79: UNITED STATES | J79: '320250350800131136' | K79: Business Services-Other Services | L79: AMEXPLATINUM | M79: =VLOOKUP(SUBSTITUTE(J79,"'",""),Sheet1!L:M,2,FALSE) -> 67500
A80: 45691 | B80: WEGMANS ASTOR PLACE NEW YORK NY | C80: 143.78 | D80: W15608201065854293656 WEGMANS ASTOR PLACE 156 000000156 NEW YORK NY 5854293656 | E80: WEGMANS ASTOR PLACE NEW YORK NY | F80: 770 BROADWAY | G80: NEW YORK NY | H80: 10003 | I80: UNITED STATES | J80: '320250350801975154' | K80: Merchandise & Supplies-Groceries | L80: AMEXPLATINUM | M80: =VLOOKUP(SUBSTITUTE(J80,"'",""),Sheet1!L:M,2,FALSE) -> 54820
A81: 45691 | B81: KALL8 00089590000642SEATTLE WA | C81: 9.38 | D81: 73011005034 ANDY@KALL8.COM KALL8 000895900006429 SEATTLE WA ANDY@KALL8.COM | E81: KALL8 00089590000642SEATTLE WA | F81: 200 WEST MERCER ST SUITE E202 | G81: SEATTLE WA | H81: 98119 | I81: UNITED STATES | J81: '320250350808786142' | K81: Other-Miscellaneous | L81: AMEXPLATINUM | M81: =VLOOKUP(SUBSTITUTE(J81,"'",""),Sheet1!L:M,2,FALSE) -> 65700
A82: 45691 | B82: TOPTAL.COM SAN FRANCISCO CA | C82: 79 | D82: NT_RHZIIYWZ +18886043188 TOPTAL.COM SAN FRANCISCO CA +18886043188 | E82: TOPTAL.COM SAN FRANCISCO CA | F82: 548 MARKET ST 36879 | G82: SAN FRANCISCO CA | H82: 94104 | I82: UNITED STATES | J82: '320250350811109214' | K82: Merchandise & Supplies-Computer Supplies | L82: DELTARESERVE | M82: =VLOOKUP(SUBSTITUTE(J82,"'",""),Sheet1!L:M,2,FALSE) -> 64200
A83: 45692 | B83: UBER | C83: 56.35 | D83: NKS60560 UIE7GEDQ 10018 Uber Trip help.uber.com CA UIE7GEDQ 10018 | E83: Uber Trip help.uber.com CA | F83: 1455 MARKET ST 4TH FLOOR | G83: SAN FRANCISCO CA | H83: 94103 | I83: UNITED STATES | J83: '320250350794490919' | K83: Transportation-Taxis & Coach | L83: DELTARESERVE | M83: =VLOOKUP(SUBSTITUTE(J83,"'",""),Sheet1!L:M,2,FALSE) -> 61130
A84: 45692 | B84: PEACOCK NEW YORK CITY NY | C84: 7.99 | D84: US NBCU PG CABLE & PAY TV PEACOCK NEW YORK CITY NY CABLE & PAY TV | E84: PEACOCK NEW YORK CITY NY | F84: 100 UNIVERSAL CITY PLZ | G84: UNIVERSAL CITY CA | H84: 91608 | I84: UNITED STATES | J84: '320250350796145377' | K84: Communications-Cable & Internet Comm | L84: DELTARESERVE | M84: =VLOOKUP(SUBSTITUTE(J84,"'",""),Sheet1!L:M,2,FALSE) -> 54820
A85: 45692 | B85: FACTOR75 BATAVIA IL | C85: 65.36 | D85: MR029169733 18885735727 FACTOR75 BATAVIA IL 18885735727 | E85: FACTOR75 BATAVIA IL | F85: 1853 SUNCAST LN | G85: BATAVIA IL | H85: 60510 | I85: UNITED STATES | J85: '320250350798082210' | K85: Merchandise & Supplies-Groceries | L85: AMEXPLATINUM | M85: =VLOOKUP(SUBSTITUTE(J85,"'",""),Sheet1!L:M,2,FALSE) -> 54820
A86: 45692 | B86: A1010BUSD01 MSBILL.INFO | C86: 26.76 | D86: Z632XUAO4F6Z632XUAO4F6W 98052 A1010BUSD01 MSBILL.INFO Z632XUAO4F6W 98052 | E86: A1010BUSD01 MSBILL.INFO | F86: 8TH FLOOR 91 MAIN ST | G86: DALLAS TX | H86: 75202 | I86: UNITED STATES | J86: '320250350811157683' | K86: Other-Miscellaneous | L86: AMEXPLATINUM | M86: =VLOOKUP(SUBSTITUTE(J86,"'",""),Sheet1!L:M,2,FALSE) -> 64100
A87: 45692 | B87: A1010BUSD01 MSBILL.INFO | C87: 21.4 | D87: Z62ZXU7VYQGZ62ZXU7VYQGY 98052 A1010BUSD01 MSBILL.INFO Z62ZXU7VYQGY 98052 | E87: A1010BUSD01 MSBILL.INFO | F87: 8TH FLOOR 91 MAIN ST | G87: DALLAS TX | H87: 75202 | I87: UNITED STATES | J87: '320250350811161119' | K87: Other-Miscellaneous | L87: AMEXPLATINUM | M87: =VLOOKUP(SUBSTITUTE(J87,"'",""),Sheet1!L:M,2,FALSE) -> 64100
A88: 45692 | B88: A1010BUSD01 MSBILL.INFO | C88: 32.07 | D88: Z62EXU45H7YZ62EXU45H7Y4 98052 A1010BUSD01 MSBILL.INFO Z62EXU45H7Y4 98052 | E88: A1010BUSD01 MSBILL.INFO | F88: 8TH FLOOR 91 MAIN ST | G88: DALLAS TX | H88: 75202 | I88: UNITED STATES | J88: '320250350811161218' | K88: Other-Miscellaneous | L88: AMEXPLATINUM | M88: =VLOOKUP(SUBSTITUTE(J88,"'",""),Sheet1!L:M,2,FALSE) -> 64100
... A94: 45692 | B94: DELMONICOS 068880022NEW YORK NY | C94: 680 | D94: 73011005036 JLICUL@ICLOUD.COM DELMONICOS 068880022170850 NEW YORK NY JLICUL@ICLOUD.COM | E94: DELMONICOS 068880022NEW YORK NY | F94: 56 BEAVER ST FRNT A | G94: NEW YORK NY | H94: 10004 | I94: UNITED STATES | J94: '320250360837993371' | K94: Restaurant-Restaurant | L94: DELTARESERVE | M94: =VLOOKUP(SUBSTITUTE(J94,"'",""),Sheet1!L:M,2,FALSE) -> 61215
A95: 45693 | B95: Interest Charge on Pay Over Time Purchases | C95: 309.9 | D95: Interest Charge on Pay Over Time Purchases | E95: Interest Charge on Pay Over Time Purchases | J95: '150206050000513407' | K95: Fees & Adjustments-Fees & Adjustments | L95: AMEXPLATINUM | M95: =VLOOKUP(SUBSTITUTE(J95,"'",""),Sheet1!L:M,2,FALSE) -> 80100
A96: 45693 | B96: A1010BUSD01 MSBILL.INFO | C96: 24.62 | D96: Z62WXVZPPP7Z62WXVZPPP7N 98052 A1010BUSD01 MSBILL.INFO Z62WXVZPPP7N 98052 | E96: A1010BUSD01 MSBILL.INFO | F96: 8TH FLOOR 91 MAIN ST | G96: DALLAS TX | H96: 75202 | I96: UNITED STATES | J96: '320250350813179900' | K96: Other-Miscellaneous | L96: DELTARESERVE | M96: =VLOOKUP(SUBSTITUTE(J96,"'",""),Sheet1!L:M,2,FALSE) -> 64100
A97: 45693 | B97: GITHUB, INC. SAN FRANCISCO CA | C97: 4 | D97: NT_RIDPOG3P +18774484820 GITHUB, INC. SAN FRANCISCO CA +18774484820 | E97: GITHUB, INC. SAN FRANCISCO CA | F97: 275 BRANNAN ST | G97: SAN FRANCISCO CA | H97: 94107 | I97: UNITED STATES | J97: '320250360821201714' | K97: Other-Miscellaneous | L97: DELTARESERVE | M97: =VLOOKUP(SUBSTITUTE(J97,"'",""),Sheet1!L:M,2,FALSE) -> 64100
A98: 45693 | B98: UBER | C98: 39.52 | D98: EMGCY768 LMRYXXNE 10012 Uber Trip help.uber.com CA LMRYXXNE 10012 | E98: Uber Trip help.uber.com CA | F98: 1455 MARKET ST 4TH FLOOR | G98: SAN FRANCISCO CA | H98: 94103 | I98: UNITED STATES | J98: '320250360823654905' | K98: Transportation-Taxis & Coach | L98: DELTARESERVE | M98: =VLOOKUP(SUBSTITUTE(J98,"'",""),Sheet1!L:M,2,FALSE) -> 61130
A99: 45693 | B99: UBER | C99: 64.8 | D99: 4SHS9W6H YNQCSRS3 10004 Uber Trip help.uber.com CA YNQCSRS3 10004 | E99: Uber Trip help.uber.com CA | F99: 1455 MARKET ST 4TH FLOOR | G99: SAN FRANCISCO CA | H99: 94103 | I99: UNITED STATES | J99: '320250360824873967' | K99: Transportation-Taxis & Coach | L99: DELTARESERVE | M99: =VLOOKUP(SUBSTITUTE(J99,"'",""),Sheet1!L:M,2,FALSE) -> 61130
A100: 45693 | B100: OLIYO 38 0000 NEW YORK NY | C100: 29.43 | D100: 17600314 646-998-3255 OLIYO 38 0000 NEW YORK NY Description : GROCERIES/SUNDRIES Price : 0.00 646-998-3255 | E100: OLIYO 38 0000 NEW YORK NY | F100: 575 8TH AVE | G100: NEW YORK NY | H100: 10018 | I100: UNITED STATES | J100: '320250370856254678' | K100: Merchandise & Supplies-Groceries | L100: DELTARESERVE | M100: =VLOOKUP(SUBSTITUTE(J100,"'",""),Sheet1!L:M,2,FALSE) -> 54820
A101: 45694 | B101: SUSHI SAIKOU New York NY | C101: 459.68 | D101: 96mepOl8Sa3 squareup.com/receipts SUSHI SAIKOU New York NY | E101: SUSHI SAIKOU New York NY | F101: 301 ELIZABETH ST | G101: NEW YORK NY | H101: 10012 | I101: UNITED STATES | J101: '320250360817890403' | K101: Restaurant-Bar & CafÃ© | L101: DELTARESERVE | M101: =VLOOKUP(SUBSTITUTE(J101,"'",""),Sheet1!L:M,2,FALSE) -> 61215
A102: 45694 | B102: LEMONADE INSURANCE 5INTERNET NY | C102: 11.33 | D102: 35UHOP00066 HELP@LEMONADE.COM LEMONADE INSURANCE 529657 INTERNET NY HELP@LEMONADE.COM | E102: LEMONADE INSURANCE 5INTERNET NY | F102: 5 CROSBY ST FL 3 | G102: NEW YORK NY | H102: 10013 | I102: UNITED STATES | J102: '320250370841166705' | K102: Business Services-Insurance Services | L102: AMEXPLATINUM | M102: =VLOOKUP(SUBSTITUTE(J102,"'",""),Sheet1!L:M,2,FALSE) -> 54820
A103: 45694 | B103: UBER | C103: 49.04 | D103: BS0NEC5C 5F2B3NVN 10018 Uber Trip help.uber.com CA 5F2B3NVN 10018 | E103: Uber Trip help.uber.com CA | F103: 1455 MARKET ST 4TH FLOOR | G103: SAN FRANCISCO CA | H103: 94103 | I103: UNITED STATES | J103: '320250370848056798' | K103: Transportation-Taxis & Coach | L103: DELTARESERVE | M103: =VLOOKUP(SUBSTITUTE(J103,"'",""),Sheet1!L:M,2,FALSE) -> 61130
A104: 45694 | B104: SPECTRUM 855-707-7328 MO | C104: 109.99 | D104: RC901253264CABLE SVC SPECTRUM 855-707-7328 MO CABLE SVC | E104: SPECTRUM 855-707-7328 MO | F104: 12405 POWERSCOURT DR | G104: SAINT LOUIS MO | H104: 63131 | I104: UNITED STATES | J104: '320250370849131276' | K104: Communications-Cable & Internet Comm | L104: AMEXPLATINUM | M104: =VLOOKUP(SUBSTITUTE(J104,"'",""),Sheet1!L:M,2,FALSE) -> 65700
A105: 45694 | B105: UBER | C105: 57.64 | D105: 6WXB99Y9 YZF2K2OZ 10003 Uber Trip help.uber.com CA YZF2K2OZ 10003 | E105: Uber Trip help.uber.com CA | F105: 1455 MARKET ST 4TH FLOOR | G105: SAN FRANCISCO CA | H105: 94103 | I105: UNITED STATES | J105: '320250370849411469' | K105: Transportation-Taxis & Coach | L105: DELTARESERVE | M105: =VLOOKUP(SUBSTITUTE(J105,"'",""),Sheet1!L:M,2,FALSE) -> 61130
...

Sheet Sheet1
A1: Posting Date | B1: Document Type | C1: Document No. | D1: G/L Account No. | E1: Description | F1: Amount | G1: Bal. Account Type | H1: Bal. Account No. | I1: Transaction No. | J1: Entry No. | K1: Reference Text | L1: Ref Clean | M1: G/L Account No.
A2: 45658 | B2: Invoice | C2: G26192 | D2: 61131 | E2: PARKFAST PAYMENT NEWARK NJ | F2: 850 | G2: Vendor | H2: MISC | I2: 22970 | J2: 47051 | K2: '320250010944540760' | L2: =SUBSTITUTE(K2,"'","") -> 320250010944540760 | M2: 61131
A3: 45658 | B3: Invoice | C3: G26193 | D3: 65700 | E3: VERIZON WRLS RCCRNG PMTS | F3: 229.15 | G3: Vendor | H3: MISC | I3: 22950 | J3: 47011 | K3: '320250010950448554' | L3: =SUBSTITUTE(K3,"'","") -> 320250010950448554 | M3: 65700
A4: 45658 | B4: Invoice | C4: G27269 | D4: 64100 | E4: Amazon Web Services AWS.Amazon.com WA | F4: 776.64 | G4: Vendor | H4: MISC | I4: 23851 | J4: 48813 | K4: '320250020977867060' | L4: =SUBSTITUTE(K4,"'","") -> 320250020977867060 | M4: 64100
A5: 45660 | B5: Invoice | C5: G27275 | D5: 65505 | E5: STATE FARM INSURANCEBLOOMINGTON IL | F5: 105.93 | G5: Vendor | H5: MISC | I5: 24105 | J5: 49321 | K5: '320250030988788564' | L5: =SUBSTITUTE(K5,"'","") -> 320250030988788564 | M5: 65505
A6: 45660 | B6: Invoice | C6: G26195 | D6: 61130 | E6: UBER | F6: 22.51 | G6: Vendor | H6: MISC | I6: 22854 | J6: 46819 | K6: '320250030993924733' | L6: =SUBSTITUTE(K6,"'","") -> 320250030993924733 | M6: 61130
A7: 45660 | B7: Invoice | C7: G26194 | D7: 61130 | E7: UBER | F7: 19.94 | G7: Vendor | H7: MISC | I7: 22853 | J7: 46817 | K7: '320250030993947348' | L7: =SUBSTITUTE(K7,"'","") -> 320250030993947348 | M7: 61130
A8: 45660 | B8: Invoice | C8: G26196 | D8: 61130 | E8: UBER | F8: 42.82 | G8: Vendor | H8: MISC | I8: 22855 | J8: 46821 | K8: '320250030994652143' | L8: =SUBSTITUTE(K8,"'","") -> 320250030994652143 | M8: 61130
A9: 45660 | B9: Invoice | C9: G27270 | D9: 67500 | E9: CREDITSECURE CostaMesa CA | F9: 21.39 | G9: Vendor | H9: MISC | I9: 23932 | J9: 48975 | K9: '320250040025658875' | L9: =SUBSTITUTE(K9,"'","") -> 320250040025658875 | M9: 67500
A10: 45660 | B10: Invoice | C10: G27271 | D10: 54820 | E10: HOUSTONST2573 2573 HOUSTON TX | F10: 9.73 | G10: Vendor | H10: MISC | I10: 24444 | J10: 49999 | K10: '320250040028119422' | L10: =SUBSTITUTE(K10,"'","") -> 320250040028119422 | M10: 54820
A11: 45660 | B11: Invoice | C11: G27272 | D11: 54820 | E11: IAH 1362U KPRC CHAN Houston TX | F11: 8.48 | G11: Vendor | H11: MISC | I11: 24445 | J11: 50001 | K11: '320250040032810577' | L11: =SUBSTITUTE(K11,"'","") -> 320250040032810577 | M11: 54820
A12: 45660 | B12: Invoice | C12: G27273 | D12: 64100 | E12: MSFT * E0500UVFU3 00MSBILL.INFO WA | F12: 21.4 | G12: Vendor | H12: MISC | I12: 23836 | J12: 48783 | K12: '320250040035107873' | L12: =SUBSTITUTE(K12,"'","") -> 320250040035107873 | M12: 64100
A13: 45660 | B13: Invoice | C13: G27274 | D13: 54820 | E13: NYX=VENDINGCUSTOMERSCHULA VISTA CA | F13: 5.5 | G13: Vendor | H13: MISC | I13: 24446 | J13: 50003 | K13: '320250040036686356' | L13: =SUBSTITUTE(K13,"'","") -> 320250040036686356 | M13: 54820
... A1792: 45955 | B1792: Invoice | C1792: G29134 | D1792: 61130 | E1792: UBER | F1792: 53.01 | G1792: Vendor | H1792: MISC | I1792: 26906 | J1792: 54934 | K1792: '320252980032626229' | L1792: =SUBSTITUTE(K1792,"'","") -> 320252980032626229 | M1792: 61130

Sheet Sheet5
A3: Row Labels | B3: Sum of Amount
A4: 54820 | B4: 85478.61 | D4: 54820 | E4: 85650.61 | F4: =D4<>G4 -> FALSE | G4: 54820 | H4: 85478.61 | I4: =H4<>E4 -> TRUE
A5: 61100 | B5: 16569.53 | D5: 61100 | E5: 16569.53 | F5: =D5<>G5 -> FALSE | G5: 61100 | H5: 16569.53 | I5: =H5<>E5 -> FALSE
A6: 61110 | B6: 19083.2 | D6: 61110 | E6: 19083.2 | F6: =D6<>G6 -> FALSE | G6: 61110 | H6: 19083.2 | I6: =H6<>E6 -> FALSE
A7: 61120 | B7: 13385.71 | D7: 61120 | E7: 13385.71 | F7: =D7<>G7 -> FALSE | G7: 61120 | H7: 13385.71 | I7: =H7<>E7 -> FALSE
A8: 61130 | B8: 11884.24 | D8: 61130 | E8: 11884.24 | F8: =D8<>G8 -> FALSE | G8: 61130 | H8: 11884.24 | I8: =H8<>E8 -> FALSE
A9: 61131 | B9: 14661.71 | D9: 61131 | E9: 14661.71 | F9: =D9<>G9 -> FALSE | G9: 61131 | H9: 14661.71 | I9: =H9<>E9 -> FALSE
A10: 61133 | B10: 43.5 | D10: 61133 | E10: 43.5 | F10: =D10<>G10 -> FALSE | G10: 61133 | H10: 43.5 | I10: =H10<>E10 -> FALSE
A11: 61200 | B11: 50.69 | D11: 61200 | E11: 50.69 | F11: =D11<>G11 -> FALSE | G11: 61200 | H11: 50.69 | I11: =H11<>E11 -> FALSE
A12: 61215 | B12: 48702.89 | D12: 61215 | E12: 48702.89 | F12: =D12<>G12 -> FALSE | G12: 61215 | H12: 48702.89 | I12: =H12<>E12 -> FALSE
A13: 63100 | B13: 968.3 | D13: 63100 | E13: 968.3 | F13: =D13<>G13 -> FALSE | G13: 63100 | H13: 968.3 | I13: =H13<>E13 -> FALSE
A14: 64100 | B14: 18285.84 | D14: 64100 | E14: 18285.84 | F14: =D14<>G14 -> FALSE | G14: 64100 | H14: 18285.84 | I14: =H14<>E14 -> FALSE
A15: 64101 | B15: 12825.6 | D15: 64101 | E15: 12825.6 | F15: =D15<>G15 -> FALSE | G15: 64101 | H15: 12825.6 | I15: =H15<>E15 -> FALSE
... A22: 80100 | B22: 6484.82 | D22: 80100 | E22: 6484.82 | F22: =D22<>G22 -> FALSE | G22: 80100 | H22: 6484.82 | I22: =H22<>E22 -> FALSE
A23: #N/A | B23: -259021.51
A24: Grand Total | B24: 20963.24
